easy_module_attribute_getter/__init__.py
easy_module_attribute_getter/custom_transforms.py
easy_module_attribute_getter/easy_module_attribute_getter.py
easy_module_attribute_getter/pytorch_getter.py
easy_module_attribute_getter/utils.py
easy_module_attribute_getter/yaml_reader.py
easy_module_attribute_getter-0.9.41.dist-info/LICENSE
easy_module_attribute_getter-0.9.41.dist-info/METADATA
easy_module_attribute_getter-0.9.41.dist-info/WHEEL
easy_module_attribute_getter-0.9.41.dist-info/top_level.txt
easy_module_attribute_getter-0.9.41.dist-info/RECORD
