Metadata-Version: 2.1
Name: easy-module-attribute-getter
Version: 0.9.41
Summary: Select module classes and functions using yaml, without any if-statements.
Home-page: https://github.com/KevinMusgrave/easy-module-attribute-getter
Author: Kevin Musgrave
Author-email: tkm45@cornell.edu
License: UNKNOWN
Platform: UNKNOWN
Classifier: Programming Language :: Python :: 3
Classifier: License :: OSI Approved :: MIT License
Classifier: Operating System :: OS Independent
Requires-Python: >=3.0
Requires-Dist: PyYAML (>=5.3.1)
Requires-Dist: torchvision (>=0.4.0)
